{
  "examples": {
    "counter": "./packages/translator/src/__tests__/fixtures/basic-counter/template.marko"
  },
  "results": [
    {
      "name": "*",
      "total": {
        "min": 10500,
        "gzip": 4686,
        "brotli": 4211
      }
    },
    {
      "name": "counter",
      "user": {
        "min": 382,
        "gzip": 271,
        "brotli": 237
      },
      "runtime": {
        "min": 4191,
        "gzip": 2010,
        "brotli": 1791
      },
      "total": {
        "min": 4573,
        "gzip": 2281,
        "brotli": 2028
      }
    }
  ]
}