{
  "examples": {
    "counter": "./packages/translator-tags/src/__tests__/fixtures/basic-counter/template.marko",
    "comments": "./packages/translator-tags/src/__tests__/fixtures/basic-inert-collapsible-tree/template.marko"
  },
  "results": [
    {
      "name": "*",
      "total": {
        "min": 13120,
        "gzip": 5613,
        "brotli": 5141
      }
    },
    {
      "name": "counter",
      "user": {
        "min": 351,
        "gzip": 277,
        "brotli": 235
      },
      "runtime": {
        "min": 4160,
        "gzip": 1932,
        "brotli": 1726
      },
      "total": {
        "min": 4511,
        "gzip": 2209,
        "brotli": 1961
      }
    },
    {
      "name": "counter 💧",
      "user": {
        "min": 204,
        "gzip": 180,
        "brotli": 152
      },
      "runtime": {
        "min": 2669,
        "gzip": 1364,
        "brotli": 1223
      },
      "total": {
        "min": 2873,
        "gzip": 1544,
        "brotli": 1375
      }
    },
    {
      "name": "comments",
      "user": {
        "min": 1248,
        "gzip": 705,
        "brotli": 646
      },
      "runtime": {
        "min": 7604,
        "gzip": 3519,
        "brotli": 3207
      },
      "total": {
        "min": 8852,
        "gzip": 4224,
        "brotli": 3853
      }
    },
    {
      "name": "comments 💧",
      "user": {
        "min": 984,
        "gzip": 582,
        "brotli": 541
      },
      "runtime": {
        "min": 8109,
        "gzip": 3723,
        "brotli": 3388
      },
      "total": {
        "min": 9093,
        "gzip": 4305,
        "brotli": 3929
      }
    }
  ]
}