{
  "examples": {
    "counter": "./packages/runtime-tags/src/__tests__/fixtures/basic-counter/template.marko",
    "comments": "./packages/runtime-tags/src/__tests__/fixtures/basic-inert-collapsible-tree/template.marko"
  },
  "results": [
    {
      "name": "*",
      "total": {
        "min": 17925,
        "brotli": 6744
      }
    },
    {
      "name": "counter",
      "user": {
        "min": 189,
        "brotli": 144
      },
      "runtime": {
        "min": 4075,
        "brotli": 1784
      },
      "total": {
        "min": 4264,
        "brotli": 1928
      }
    },
    {
      "name": "counter 💧",
      "user": {
        "min": 111,
        "brotli": 100
      },
      "runtime": {
        "min": 3448,
        "brotli": 1555
      },
      "total": {
        "min": 3559,
        "brotli": 1655
      }
    },
    {
      "name": "comments",
      "user": {
        "min": 1044,
        "brotli": 512
      },
      "runtime": {
        "min": 7267,
        "brotli": 3061
      },
      "total": {
        "min": 8311,
        "brotli": 3573
      }
    },
    {
      "name": "comments 💧",
      "user": {
        "min": 145,
        "brotli": 120
      },
      "runtime": {
        "min": 3650,
        "brotli": 1620
      },
      "total": {
        "min": 3795,
        "brotli": 1740
      }
    }
  ]
}